[
  {
    "location": "Visakhapatnam",
    "date_time": "2025-09-14T12:00:00",
    "temperature_c_": 27.5,
    "ph": 8.1,
    "dissolved_oxygen_mg_l_": 6.2,
    "salinity_ppt_": 34.8,
    "chlorophyll_a_mg_m³_": 0.9,
    "turbidity_ntu_": 1.2,
    "hydrocarbons_µg_l_": 0.02,
    "water_type": "Coastal Sea",
    "nitrate_µm_": "2 – 6",
    "phosphate_µm_": "0.2 – 0.50",
    "ocean_currents_m_s_": "0.4 – 0.9",
    "wave_height_m_": "1 – 2",
    "status": "Blue",
    "latitude": null,
    "longitude": null
  },
  {
    "location": "Visakhapatnam",
    "date_time": "2025-09-14T18:00:00",
    "temperature_c_": 27.8,
    "ph": 8.0,
    "dissolved_oxygen_mg_l_": 5.4,
    "salinity_ppt_": 34.7,
    "chlorophyll_a_mg_m³_": 1.1,
    "turbidity_ntu_": 1.3,
    "hydrocarbons_µg_l_": 0.03,
    "water_type": "Coastal Sea",
    "nitrate_µm_": "2 - 6",
    "phosphate_µm_": "0.2 – 0.5",
    "ocean_currents_m_s_": "0.4 – 0.9",
    "wave_height_m_": "1 – 2",
    "status": "Green",
    "latitude": null,
    "longitude": null
  },
  {
    "location": "Kochi",
    "date_time": "2025-09-14T12:00:00",
    "temperature_c_": 29.1,
    "ph": 7.9,
    "dissolved_oxygen_mg_l_": 4.8,
    "salinity_ppt_": 33.5,
    "chlorophyll_a_mg_m³_": 1.4,
    "turbidity_ntu_": 1.5,
    "hydrocarbons_µg_l_": 0.05,
    "water_type": "Coastal Sea",
    "nitrate_µm_": "2 - 6",
    "phosphate_µm_": "0.2 – 0.5",
    "ocean_currents_m_s_": "0.4 – 0.9",
    "wave_height_m_": "1 – 2",
    "status": "Green",
    "latitude": null,
    "longitude": null
  },
  {
    "location": "Kochi",
    "date_time": "2025-09-14T18:00:00",
    "temperature_c_": 29.3,
    "ph": 7.8,
    "dissolved_oxygen_mg_l_": 3.1,
    "salinity_ppt_": 33.4,
    "chlorophyll_a_mg_m³_": 1.7,
    "turbidity_ntu_": 1.9,
    "hydrocarbons_µg_l_": 0.07,
    "water_type": "Coastal Sea",
    "nitrate_µm_": "2 - 6",
    "phosphate_µm_": "0.2 – 0.5",
    "ocean_currents_m_s_": "0.4 – 0.9",
    "wave_height_m_": "1 – 2",
    "status": "Red",
    "latitude": null,
    "longitude": null
  },
  {
    "location": "Bay of Bengal",
    "date_time": "2025-09-16T15:57:57",
    "temperature_c_": 27.5,
    "ph": 8.1,
    "dissolved_oxygen_mg_l_": 6.2,
    "salinity_ppt_": 34.8,
    "chlorophyll_a_mg_m³_": 0.9,
    "turbidity_ntu_": 1.2,
    "hydrocarbons_µg_l_": 0.02,
    "water_type": "Open Ocean",
    "nitrate_µm_": "1 – 3",
    "phosphate_µm_": "0.1 – 0.3",
    "ocean_currents_m_s_": "0.8 – 1.5",
    "wave_height_m_": "1.5 – 3",
    "status": "Blue",
    "latitude": null,
    "longitude": null
  },
  {
    "location": "Bay of Bengal",
    "date_time": "2025-09-16T13:04:51",
    "temperature_c_": 27.3,
    "ph": 8.0,
    "dissolved_oxygen_mg_l_": 6.5,
    "salinity_ppt_": 34.7,
    "chlorophyll_a_mg_m³_": 1.0,
    "turbidity_ntu_": 1.1,
    "hydrocarbons_µg_l_": 0.03,
    "water_type": "Open Ocean",
    "nitrate_µm_": "1 – 3",
    "phosphate_µm_": "0.1 – 0.3",
    "ocean_currents_m_s_": "0.8 – 1.5",
    "wave_height_m_": "1.5 – 3",
    "status": "Blue",
    "latitude": null,
    "longitude": null
  },
  {
    "location": "Bay of Bengal",
    "date_time": "2025-09-16T10:04:51",
    "temperature_c_": 27.8,
    "ph": 8.2,
    "dissolved_oxygen_mg_l_": 6.3,
    "salinity_ppt_": 34.9,
    "chlorophyll_a_mg_m³_": 0.95,
    "turbidity_ntu_": 1.3,
    "hydrocarbons_µg_l_": 0.025,
    "water_type": "Open Ocean",
    "nitrate_µm_": "1 – 3",
    "phosphate_µm_": "0.1 – 0.3",
    "ocean_currents_m_s_": "0.8 – 1.5",
    "wave_height_m_": "1.5 – 3",
    "status": "Green",
    "latitude": null,
    "longitude": null
  },
  {
    "location": "Arabian Sea",
    "date_time": "2025-09-16T06:00:00",
    "temperature_c_": 28.3,
    "ph": 8.03,
    "dissolved_oxygen_mg_l_": 5.7,
    "salinity_ppt_": 35.3,
    "chlorophyll_a_mg_m³_": 0.86,
    "turbidity_ntu_": 1.1,
    "hydrocarbons_µg_l_": 0.021,
    "water_type": "Open Ocean",
    "nitrate_µm_": "1 – 3",
    "phosphate_µm_": "0.1 – 0.3",
    "ocean_currents_m_s_": "0.8 – 1.5",
    "wave_height_m_": "1.5 – 3",
    "status": "Green",
    "latitude": null,
    "longitude": null
  },
  {
    "location": "Arabian Sea",
    "date_time": "2025-09-16T09:00:00",
    "temperature_c_": 27.2,
    "ph": 7.98,
    "dissolved_oxygen_mg_l_": 5.4,
    "salinity_ppt_": 35.1,
    "chlorophyll_a_mg_m³_": 0.83,
    "turbidity_ntu_": 0.9,
    "hydrocarbons_µg_l_": 0.026,
    "water_type": "Open Ocean",
    "nitrate_µm_": "1 – 3",
    "phosphate_µm_": "0.1 – 0.3",
    "ocean_currents_m_s_": "0.8 – 1.5",
    "wave_height_m_": "1.5 – 3",
    "status": "Red",
    "latitude": null,
    "longitude": null
  },
  {
    "location": "Arabian Sea",
    "date_time": "2025-09-16T12:00:00",
    "temperature_c_": 27.2,
    "ph": 8.15,
    "dissolved_oxygen_mg_l_": 5.8,
    "salinity_ppt_": 35.2,
    "chlorophyll_a_mg_m³_": 0.87,
    "turbidity_ntu_": 1.0,
    "hydrocarbons_µg_l_": 0.023,
    "water_type": "Open Ocean",
    "nitrate_µm_": "1 – 3",
    "phosphate_µm_": "0.1 – 0.3",
    "ocean_currents_m_s_": "0.8 – 1.5",
    "wave_height_m_": "1.5 – 3",
    "status": "Green",
    "latitude": null,
    "longitude": null
  },
  {
    "location": "Indian Ocean",
    "date_time": "2025-09-16T06:00:00",
    "temperature_c_": 28.7,
    "ph": 8.1,
    "dissolved_oxygen_mg_l_": 5.8,
    "salinity_ppt_": 34.8,
    "chlorophyll_a_mg_m³_": 0.51,
    "turbidity_ntu_": 0.5,
    "hydrocarbons_µg_l_": 0.004,
    "water_type": "Open Ocean",
    "nitrate_µm_": "1 – 3",
    "phosphate_µm_": "0.1 – 0.3",
    "ocean_currents_m_s_": "0.8 – 1.5",
    "wave_height_m_": "1.5 – 3",
    "status": "Green",
    "latitude": null,
    "longitude": null
  },
  {
    "location": "Indian Ocean",
    "date_time": "2025-09-16T12:00:00",
    "temperature_c_": 28.0,
    "ph": 8.03,
    "dissolved_oxygen_mg_l_": 6.3,
    "salinity_ppt_": 35.0,
    "chlorophyll_a_mg_m³_": 0.58,
    "turbidity_ntu_": 0.7,
    "hydrocarbons_µg_l_": 0.02,
    "water_type": "Open Ocean",
    "nitrate_µm_": "1 – 3",
    "phosphate_µm_": "0.1 – 0.3",
    "ocean_currents_m_s_": "0.8 – 1.5",
    "wave_height_m_": "1.5 – 3",
    "status": "Blue",
    "latitude": null,
    "longitude": null
  },
  {
    "location": "Laccadive Sea",
    "date_time": "2025-09-16T06:00:00",
    "temperature_c_": 28.4,
    "ph": 8.12,
    "dissolved_oxygen_mg_l_": 6.5,
    "salinity_ppt_": 34.5,
    "chlorophyll_a_mg_m³_": 0.72,
    "turbidity_ntu_": 0.6,
    "hydrocarbons_µg_l_": 0.01,
    "water_type": "Open Ocean",
    "nitrate_µm_": "1 – 3",
    "phosphate_µm_": "0.1 – 0.3",
    "ocean_currents_m_s_": "0.8 – 1.5",
    "wave_height_m_": "1.5 – 3",
    "status": "Blue",
    "latitude": null,
    "longitude": null
  },
  {
    "location": "Laccadive Sea",
    "date_time": "2025-09-16T09:00:00",
    "temperature_c_": 28.1,
    "ph": 8.09,
    "dissolved_oxygen_mg_l_": 6.2,
    "salinity_ppt_": 34.6,
    "chlorophyll_a_mg_m³_": 0.8,
    "turbidity_ntu_": 0.7,
    "hydrocarbons_µg_l_": 0.015,
    "water_type": "Open Ocean",
    "nitrate_µm_": "1 – 3",
    "phosphate_µm_": "0.1 – 0.3",
    "ocean_currents_m_s_": "0.8 – 1.5",
    "wave_height_m_": "1.5 – 3",
    "status": "Green",
    "latitude": null,
    "longitude": null
  },
  {
    "location": "Laccadive Sea",
    "date_time": "2025-09-16T21:00:00",
    "temperature_c_": 27.6,
    "ph": 8.02,
    "dissolved_oxygen_mg_l_": 5.3,
    "salinity_ppt_": 34.9,
    "chlorophyll_a_mg_m³_": 0.71,
    "turbidity_ntu_": 1.2,
    "hydrocarbons_µg_l_": 0.045,
    "water_type": "Open Ocean",
    "nitrate_µm_": "1 – 3",
    "phosphate_µm_": "0.1 – 0.3",
    "ocean_currents_m_s_": "0.8 – 1.5",
    "wave_height_m_": "1.5 – 3",
    "status": "Red",
    "latitude": null,
    "longitude": null
  },
  {
    "location": "Raichak Lake",
    "date_time": "2025-09-16T06:00:00",
    "temperature_c_": 29.0,
    "ph": 7.4,
    "dissolved_oxygen_mg_l_": 4.2,
    "salinity_ppt_": 1.2,
    "chlorophyll_a_mg_m³_": 4.5,
    "turbidity_ntu_": 12.0,
    "hydrocarbons_µg_l_": 0.12,
    "water_type": "Freshwater Lakes",
    "nitrate_µm_": "5 – 20",
    "phosphate_µm_": "0.2 – 0.8",
    "ocean_currents_m_s_": "0.05 – 0.2",
    "wave_height_m_": "0.1 – 0.5",
    "status": "Red",
    "latitude": null,
    "longitude": null
  },
  {
    "location": "Raichak Lake",
    "date_time": "2025-09-16T12:00:00",
    "temperature_c_": 30.1,
    "ph": 7.6,
    "dissolved_oxygen_mg_l_": 5.1,
    "salinity_ppt_": 1.5,
    "chlorophyll_a_mg_m³_": 4.2,
    "turbidity_ntu_": 10.8,
    "hydrocarbons_µg_l_": 0.09,
    "water_type": "Freshwater Lakes",
    "nitrate_µm_": "5 – 20",
    "phosphate_µm_": "0.2 – 0.8",
    "ocean_currents_m_s_": "0.05 – 0.2",
    "wave_height_m_": "0.1 – 0.5",
    "status": "Green",
    "latitude": null,
    "longitude": null
  },
  {
    "location": "Mangalore Lake",
    "date_time": "2025-09-16T06:00:00",
    "temperature_c_": 28.4,
    "ph": 8.05,
    "dissolved_oxygen_mg_l_": 5.9,
    "salinity_ppt_": 33.8,
    "chlorophyll_a_mg_m³_": 1.8,
    "turbidity_ntu_": 3.5,
    "hydrocarbons_µg_l_": 0.03,
    "water_type": "Freshwater Lakes",
    "nitrate_µm_": "5 – 20",
    "phosphate_µm_": "0.2 – 0.8",
    "ocean_currents_m_s_": "0.05 – 0.2",
    "wave_height_m_": "0.1 – 0.5",
    "status": "Green",
    "latitude": null,
    "longitude": null
  },
  {
    "location": "Mangalore Lake",
    "date_time": "2025-09-16T09:00:00",
    "temperature_c_": 28.6,
    "ph": 8.07,
    "dissolved_oxygen_mg_l_": 6.2,
    "salinity_ppt_": 34.0,
    "chlorophyll_a_mg_m³_": 1.6,
    "turbidity_ntu_": 3.2,
    "hydrocarbons_µg_l_": 0.025,
    "water_type": "Freshwater Lakes",
    "nitrate_µm_": "5 – 20",
    "phosphate_µm_": "0.2 – 0.8",
    "ocean_currents_m_s_": "0.05 – 0.2",
    "wave_height_m_": "0.1 – 0.5",
    "status": "Blue",
    "latitude": null,
    "longitude": null
  },
  {
    "location": "Mangalore Lake",
    "date_time": "2025-09-16T21:00:00",
    "temperature_c_": 28.5,
    "ph": 8.01,
    "dissolved_oxygen_mg_l_": 5.5,
    "salinity_ppt_": 33.7,
    "chlorophyll_a_mg_m³_": 2.0,
    "turbidity_ntu_": 4.2,
    "hydrocarbons_µg_l_": 0.05,
    "water_type": "Freshwater Lakes",
    "nitrate_µm_": "5 – 20",
    "phosphate_µm_": "0.2 – 0.8",
    "ocean_currents_m_s_": "0.05 – 0.2",
    "wave_height_m_": "0.1 – 0.5",
    "status": "Red",
    "latitude": null,
    "longitude": null
  },
  {
    "location": "Andaman Sea",
    "date_time": "2025-09-16T06:00:00",
    "temperature_c_": 28.6,
    "ph": 8.14,
    "dissolved_oxygen_mg_l_": 6.6,
    "salinity_ppt_": 34.2,
    "chlorophyll_a_mg_m³_": 0.62,
    "turbidity_ntu_": 0.7,
    "hydrocarbons_µg_l_": 0.008,
    "water_type": "Open Ocean",
    "nitrate_µm_": "1 – 3",
    "phosphate_µm_": "0.1 – 0.3",
    "ocean_currents_m_s_": "0.8 – 1.5",
    "wave_height_m_": "1.5 – 3",
    "status": "Blue",
    "latitude": null,
    "longitude": null
  },
  {
    "location": "Andaman Sea",
    "date_time": "2025-09-16T12:00:00",
    "temperature_c_": 29.3,
    "ph": 8.09,
    "dissolved_oxygen_mg_l_": 6.2,
    "salinity_ppt_": 34.5,
    "chlorophyll_a_mg_m³_": 0.75,
    "turbidity_ntu_": 1.0,
    "hydrocarbons_µg_l_": 0.018,
    "water_type": "Open Ocean",
    "nitrate_µm_": "1 – 3",
    "phosphate_µm_": "0.1 – 0.3",
    "ocean_currents_m_s_": "0.8 – 1.5",
    "wave_height_m_": "1.5 – 3",
    "status": "Green",
    "latitude": null,
    "longitude": null
  },
  {
    "location": "Andaman Sea",
    "date_time": "2025-09-16T21:00:00",
    "temperature_c_": 28.4,
    "ph": 8.02,
    "dissolved_oxygen_mg_l_": 5.4,
    "salinity_ppt_": 34.1,
    "chlorophyll_a_mg_m³_": 1.1,
    "turbidity_ntu_": 1.9,
    "hydrocarbons_µg_l_": 0.045,
    "water_type": "Open Ocean",
    "nitrate_µm_": "1 – 3",
    "phosphate_µm_": "0.1 – 0.3",
    "ocean_currents_m_s_": "0.8 – 1.5",
    "wave_height_m_": "1.5 – 3",
    "status": "Red",
    "latitude": null,
    "longitude": null
  },
  {
    "location": "Gulf of Kutch",
    "date_time": "2025-09-16T06:00:00",
    "temperature_c_": 28.7,
    "ph": 8.18,
    "dissolved_oxygen_mg_l_": 5.9,
    "salinity_ppt_": 36.0,
    "chlorophyll_a_mg_m³_": 1.2,
    "turbidity_ntu_": 2.5,
    "hydrocarbons_µg_l_": 0.02,
    "water_type": "Semi-enclosed/Estuary",
    "nitrate_µm_": "5 – 15",
    "phosphate_µm_": "0.5 – 1.5",
    "ocean_currents_m_s_": "0.3 – 0.7",
    "wave_height_m_": "0.8 – 1.5",
    "status": "Green",
    "latitude": null,
    "longitude": null
  },
  {
    "location": "Gulf of Kutch",
    "date_time": "2025-09-16T09:00:00",
    "temperature_c_": 29.0,
    "ph": 8.15,
    "dissolved_oxygen_mg_l_": 6.1,
    "salinity_ppt_": 36.2,
    "chlorophyll_a_mg_m³_": 1.0,
    "turbidity_ntu_": 2.2,
    "hydrocarbons_µg_l_": 0.018,
    "water_type": "Semi-enclosed/Estuary",
    "nitrate_µm_": "5 – 15",
    "phosphate_µm_": "0.5 – 1.5",
    "ocean_currents_m_s_": "0.3 – 0.7",
    "wave_height_m_": "0.8 – 1.5",
    "status": "Blue",
    "latitude": null,
    "longitude": null
  },
  {
    "location": "Gulf of Kutch",
    "date_time": "2025-09-16T21:00:00",
    "temperature_c_": 28.9,
    "ph": 8.03,
    "dissolved_oxygen_mg_l_": 4.8,
    "salinity_ppt_": 36.2,
    "chlorophyll_a_mg_m³_": 2.0,
    "turbidity_ntu_": 4.5,
    "hydrocarbons_µg_l_": 0.08,
    "water_type": "Semi-enclosed/Estuary",
    "nitrate_µm_": "5 – 15",
    "phosphate_µm_": "0.5 – 1.5",
    "ocean_currents_m_s_": "0.3 – 0.7",
    "wave_height_m_": "0.8 – 1.5",
    "status": "Red",
    "latitude": null,
    "longitude": null
  },
  {
    "location": "Gulf of Khambhat",
    "date_time": "2025-09-16T06:00:00",
    "temperature_c_": 28.9,
    "ph": 7.8,
    "dissolved_oxygen_mg_l_": 4.5,
    "salinity_ppt_": 30.5,
    "chlorophyll_a_mg_m³_": 3.2,
    "turbidity_ntu_": 25.0,
    "hydrocarbons_µg_l_": 0.09,
    "water_type": "Semi-enclosed/Estuary",
    "nitrate_µm_": "5 – 15",
    "phosphate_µm_": "0.5 – 1.5",
    "ocean_currents_m_s_": "0.3 – 0.7",
    "wave_height_m_": "0.8 – 1.5",
    "status": "Red",
    "latitude": null,
    "longitude": null
  },
  {
    "location": "Gulf of Khambhat",
    "date_time": "2025-09-16T12:00:00",
    "temperature_c_": 29.6,
    "ph": 8.0,
    "dissolved_oxygen_mg_l_": 5.2,
    "salinity_ppt_": 31.0,
    "chlorophyll_a_mg_m³_": 2.7,
    "turbidity_ntu_": 20.2,
    "hydrocarbons_µg_l_": 0.06,
    "water_type": "Semi-enclosed/Estuary",
    "nitrate_µm_": "5 – 15",
    "phosphate_µm_": "0.5 – 1.5",
    "ocean_currents_m_s_": "0.3 – 0.7",
    "wave_height_m_": "0.8 – 1.5",
    "status": "Green",
    "latitude": null,
    "longitude": null
  },
  {
    "location": "Gulf of Mannar",
    "date_time": "2025-09-16T06:00:00",
    "temperature_c_": 28.3,
    "ph": 8.12,
    "dissolved_oxygen_mg_l_": 6.4,
    "salinity_ppt_": 34.7,
    "chlorophyll_a_mg_m³_": 0.9,
    "turbidity_ntu_": 1.2,
    "hydrocarbons_µg_l_": 0.015,
    "water_type": "Open Ocean",
    "nitrate_µm_": "1 – 3",
    "phosphate_µm_": "0.1 – 0.3",
    "ocean_currents_m_s_": "0.8 – 1.5",
    "wave_height_m_": "1.5 – 3",
    "status": "Blue",
    "latitude": null,
    "longitude": null
  },
  {
    "location": "Gulf of Mannar",
    "date_time": "2025-09-16T12:00:00",
    "temperature_c_": 29.0,
    "ph": 8.08,
    "dissolved_oxygen_mg_l_": 6.0,
    "salinity_ppt_": 35.0,
    "chlorophyll_a_mg_m³_": 1.3,
    "turbidity_ntu_": 1.8,
    "hydrocarbons_µg_l_": 0.025,
    "water_type": "Open Ocean",
    "nitrate_µm_": "1 – 3",
    "phosphate_µm_": "0.1 – 0.3",
    "ocean_currents_m_s_": "0.8 – 1.5",
    "wave_height_m_": "1.5 – 3",
    "status": "Green",
    "latitude": null,
    "longitude": null
  },
  {
    "location": "Gulf of Mannar",
    "date_time": "2025-09-16T18:00:00",
    "temperature_c_": 28.9,
    "ph": 8.02,
    "dissolved_oxygen_mg_l_": 5.5,
    "salinity_ppt_": 34.8,
    "chlorophyll_a_mg_m³_": 1.7,
    "turbidity_ntu_": 2.4,
    "hydrocarbons_µg_l_": 0.042,
    "water_type": "Open Ocean",
    "nitrate_µm_": "1 – 3",
    "phosphate_µm_": "0.1 – 0.3",
    "ocean_currents_m_s_": "0.8 – 1.5",
    "wave_height_m_": "1.5 – 3",
    "status": "Red",
    "latitude": null,
    "longitude": null
  },
  {
    "location": "Palk Strait",
    "date_time": "2025-09-16T06:00:00",
    "temperature_c_": 28.5,
    "ph": 8.02,
    "dissolved_oxygen_mg_l_": 5.0,
    "salinity_ppt_": 33.5,
    "chlorophyll_a_mg_m³_": 2.4,
    "turbidity_ntu_": 6.0,
    "hydrocarbons_µg_l_": 0.04,
    "water_type": "Open Ocean",
    "nitrate_µm_": "1 – 3",
    "phosphate_µm_": "0.1 – 0.3",
    "ocean_currents_m_s_": "0.8 – 1.5",
    "wave_height_m_": "1.5 – 3",
    "status": "Green",
    "latitude": null,
    "longitude": null
  },
  {
    "location": "Palk Strait",
    "date_time": "2025-09-16T09:00:00",
    "temperature_c_": 28.8,
    "ph": 8.0,
    "dissolved_oxygen_mg_l_": 4.8,
    "salinity_ppt_": 33.7,
    "chlorophyll_a_mg_m³_": 2.6,
    "turbidity_ntu_": 6.5,
    "hydrocarbons_µg_l_": 0.05,
    "water_type": "Open Ocean",
    "nitrate_µm_": "1 – 3",
    "phosphate_µm_": "0.1 – 0.3",
    "ocean_currents_m_s_": "0.8 – 1.5",
    "wave_height_m_": "1.5 – 3",
    "status": "Red",
    "latitude": null,
    "longitude": null
  },
  {
    "location": "Strait of Malacca",
    "date_time": "2025-09-16T06:00:00",
    "temperature_c_": 29.1,
    "ph": 7.95,
    "dissolved_oxygen_mg_l_": 4.8,
    "salinity_ppt_": 32.9,
    "chlorophyll_a_mg_m³_": 1.8,
    "turbidity_ntu_": 4.2,
    "hydrocarbons_µg_l_": 0.06,
    "water_type": "Open Ocean",
    "nitrate_µm_": "1 – 3",
    "phosphate_µm_": "0.1 – 0.3",
    "ocean_currents_m_s_": "0.8 – 1.5",
    "wave_height_m_": "1.5 – 3",
    "status": "Red",
    "latitude": null,
    "longitude": null
  },
  {
    "location": "Strait of Malacca",
    "date_time": "2025-09-17T03:00:00",
    "temperature_c_": 28.8,
    "ph": 7.98,
    "dissolved_oxygen_mg_l_": 5.3,
    "salinity_ppt_": 32.7,
    "chlorophyll_a_mg_m³_": 1.7,
    "turbidity_ntu_": 3.7,
    "hydrocarbons_µg_l_": 0.055,
    "water_type": "Open Ocean",
    "nitrate_µm_": "1 – 3",
    "phosphate_µm_": "0.1 – 0.3",
    "ocean_currents_m_s_": "0.8 – 1.5",
    "wave_height_m_": "1.5 – 3",
    "status": "Green",
    "latitude": null,
    "longitude": null
  },
  {
    "location": "Wular Lake",
    "date_time": "2025-09-16T06:00:00",
    "temperature_c_": 20.1,
    "ph": 7.65,
    "dissolved_oxygen_mg_l_": 7.2,
    "salinity_ppt_": 0.3,
    "chlorophyll_a_mg_m³_": 5.2,
    "turbidity_ntu_": 8.1,
    "hydrocarbons_µg_l_": 0.02,
    "water_type": "Freshwater Lakes",
    "nitrate_µm_": "5 – 20",
    "phosphate_µm_": "0.2 – 0.8",
    "ocean_currents_m_s_": "0.05 – 0.2",
    "wave_height_m_": "0.1 – 0.5",
    "status": "Green",
    "latitude": null,
    "longitude": null
  },
  {
    "location": "Wular Lake",
    "date_time": "2025-09-16T12:00:00",
    "temperature_c_": 22.3,
    "ph": 7.58,
    "dissolved_oxygen_mg_l_": 5.9,
    "salinity_ppt_": 0.3,
    "chlorophyll_a_mg_m³_": 6.4,
    "turbidity_ntu_": 10.2,
    "hydrocarbons_µg_l_": 0.032,
    "water_type": "Freshwater Lakes",
    "nitrate_µm_": "5 – 20",
    "phosphate_µm_": "0.2 – 0.8",
    "ocean_currents_m_s_": "0.05 – 0.2",
    "wave_height_m_": "0.1 – 0.5",
    "status": "Red",
    "latitude": null,
    "longitude": null
  },
  {
    "location": "Dal Lake",
    "date_time": "2025-09-16T06:00:00",
    "temperature_c_": 19.2,
    "ph": 0.45,
    "dissolved_oxygen_mg_l_": 6.8,
    "salinity_ppt_": 0.2,
    "chlorophyll_a_mg_m³_": 8.5,
    "turbidity_ntu_": 9.8,
    "hydrocarbons_µg_l_": 0.03,
    "water_type": "Freshwater Lakes",
    "nitrate_µm_": "5 – 20",
    "phosphate_µm_": "0.2 – 0.8",
    "ocean_currents_m_s_": "0.05 – 0.2",
    "wave_height_m_": "0.1 – 0.5",
    "status": "Green",
    "latitude": null,
    "longitude": null
  },
  {
    "location": "Dal Lake",
    "date_time": "2025-09-16T09:00:00",
    "temperature_c_": 20.1,
    "ph": 7.4,
    "dissolved_oxygen_mg_l_": 6.2,
    "salinity_ppt_": 0.2,
    "chlorophyll_a_mg_m³_": 9.2,
    "turbidity_ntu_": 10.5,
    "hydrocarbons_µg_l_": 0.038,
    "water_type": "Freshwater Lakes",
    "nitrate_µm_": "5 – 20",
    "phosphate_µm_": "0.2 – 0.8",
    "ocean_currents_m_s_": "0.05 – 0.2",
    "wave_height_m_": "0.1 – 0.5",
    "status": "Red",
    "latitude": null,
    "longitude": null
  },
  {
    "location": "Loktak Lake",
    "date_time": "2025-09-16T06:00:00",
    "temperature_c_": 24.1,
    "ph": 7.4,
    "dissolved_oxygen_mg_l_": 6.9,
    "salinity_ppt_": 0.3,
    "chlorophyll_a_mg_m³_": 5.5,
    "turbidity_ntu_": 7.6,
    "hydrocarbons_µg_l_": 0.018,
    "water_type": "Large Lagoon/Estuary Lakes",
    "nitrate_µm_": "10 – 30",
    "phosphate_µm_": "1 – 2",
    "ocean_currents_m_s_": "0.1 – 0.3",
    "wave_height_m_": "0.2 – 0.8",
    "status": "Green",
    "latitude": null,
    "longitude": null
  },
  {
    "location": "Loktak Lake",
    "date_time": "2025-09-16T12:00:00",
    "temperature_c_": 26.2,
    "ph": 7.28,
    "dissolved_oxygen_mg_l_": 5.3,
    "salinity_ppt_": 0.3,
    "chlorophyll_a_mg_m³_": 6.9,
    "turbidity_ntu_": 9.8,
    "hydrocarbons_µg_l_": 0.036,
    "water_type": "Large Lagoon/Estuary Lakes",
    "nitrate_µm_": "10 – 30",
    "phosphate_µm_": "1 – 2",
    "ocean_currents_m_s_": "0.1 – 0.3",
    "wave_height_m_": "0.2 – 0.8",
    "status": "Red",
    "latitude": null,
    "longitude": null
  },
  {
    "location": "Chilika Lake",
    "date_time": "2025-09-16T12:00:00",
    "temperature_c_": 29.1,
    "ph": 7.72,
    "dissolved_oxygen_mg_l_": 5.2,
    "salinity_ppt_": 11.6,
    "chlorophyll_a_mg_m³_": 6.0,
    "turbidity_ntu_": 9.0,
    "hydrocarbons_µg_l_": 0.05,
    "water_type": "Large Lagoon/Estuary Lakes",
    "nitrate_µm_": "10 – 30",
    "phosphate_µm_": "1 – 2",
    "ocean_currents_m_s_": "0.1 – 0.3",
    "wave_height_m_": "0.2 – 0.8",
    "status": "Red",
    "latitude": null,
    "longitude": null
  },
  {
    "location": "Chilika Lake",
    "date_time": "2025-09-16T06:00:00",
    "temperature_c_": 27.2,
    "ph": 7.8,
    "dissolved_oxygen_mg_l_": 6.5,
    "salinity_ppt_": 10.5,
    "chlorophyll_a_mg_m³_": 4.8,
    "turbidity_ntu_": 7.1,
    "hydrocarbons_µg_l_": 0.03,
    "water_type": "Large Lagoon/Estuary Lakes",
    "nitrate_µm_": "10 – 30",
    "phosphate_µm_": "1 – 2",
    "ocean_currents_m_s_": "0.1 – 0.3",
    "wave_height_m_": "0.2 – 0.8",
    "status": "Green",
    "latitude": null,
    "longitude": null
  },
  {
    "location": "Pulicat Lake",
    "date_time": "2025-09-16T06:00:00",
    "temperature_c_": 27.5,
    "ph": 7.82,
    "dissolved_oxygen_mg_l_": 6.7,
    "salinity_ppt_": 15.0,
    "chlorophyll_a_mg_m³_": 3.9,
    "turbidity_ntu_": 6.8,
    "hydrocarbons_µg_l_": 0.028,
    "water_type": "Large Lagoon/Estuary Lakes",
    "nitrate_µm_": "10 – 30",
    "phosphate_µm_": "1 – 2",
    "ocean_currents_m_s_": "0.1 – 0.3",
    "wave_height_m_": "0.2 – 0.8",
    "status": "Green",
    "latitude": null,
    "longitude": null
  },
  {
    "location": "Pulicat Lake",
    "date_time": "2025-09-16T12:00:00",
    "temperature_c_": 29.4,
    "ph": 7.74,
    "dissolved_oxygen_mg_l_": 5.4,
    "salinity_ppt_": 16.2,
    "chlorophyll_a_mg_m³_": 5.1,
    "turbidity_ntu_": 8.7,
    "hydrocarbons_µg_l_": 0.046,
    "water_type": "Large Lagoon/Estuary Lakes",
    "nitrate_µm_": "10 – 30",
    "phosphate_µm_": "1 – 2",
    "ocean_currents_m_s_": "0.1 – 0.3",
    "wave_height_m_": "0.2 – 0.8",
    "status": "Red",
    "latitude": null,
    "longitude": null
  },
  {
    "location": "Vembanad Lake",
    "date_time": "2025-09-16T12:00:00",
    "temperature_c_": 28.6,
    "ph": 7.24,
    "dissolved_oxygen_mg_l_": 4.1,
    "salinity_ppt_": 4.6,
    "chlorophyll_a_mg_m³_": 8.5,
    "turbidity_ntu_": 15.6,
    "hydrocarbons_µg_l_": 0.061,
    "water_type": "Large Lagoon/Estuary Lakes",
    "nitrate_µm_": "10 – 30",
    "phosphate_µm_": "1 – 2",
    "ocean_currents_m_s_": "0.1 – 0.3",
    "wave_height_m_": "0.2 – 0.8",
    "status": "Red",
    "latitude": null,
    "longitude": null
  },
  {
    "location": "Vembanad Lake",
    "date_time": "2025-09-17T03:00:00",
    "temperature_c_": 26.2,
    "ph": 7.36,
    "dissolved_oxygen_mg_l_": 6.0,
    "salinity_ppt_": 2.9,
    "chlorophyll_a_mg_m³_": 5.8,
    "turbidity_ntu_": 11.3,
    "hydrocarbons_µg_l_": 0.029,
    "water_type": "Large Lagoon/Estuary Lakes",
    "nitrate_µm_": "10 – 30",
    "phosphate_µm_": "1 – 2",
    "ocean_currents_m_s_": "0.1 – 0.3",
    "wave_height_m_": "0.2 – 0.8",
    "status": "Green",
    "latitude": null,
    "longitude": null
  },
  {
    "location": "Sambhar Salt Lake",
    "date_time": "2025-09-16T12:00:00",
    "temperature_c_": 30.6,
    "ph": 8.53,
    "dissolved_oxygen_mg_l_": 4.0,
    "salinity_ppt_": 79.6,
    "chlorophyll_a_mg_m³_": 4.0,
    "turbidity_ntu_": 13.9,
    "hydrocarbons_µg_l_": 0.037,
    "water_type": "Saline Lakes",
    "nitrate_µm_": "15 – 40",
    "phosphate_µm_": "1 – 3",
    "ocean_currents_m_s_": "0.05 – 0.2",
    "wave_height_m_": "0.1 – 0.5",
    "status": "Red",
    "latitude": null,
    "longitude": null
  },
  {
    "location": "Sambhar Salt Lake",
    "date_time": "2025-09-17T00:00:00",
    "temperature_c_": 24.6,
    "ph": 8.42,
    "dissolved_oxygen_mg_l_": 6.4,
    "salinity_ppt_": 66.2,
    "chlorophyll_a_mg_m³_": 2.2,
    "turbidity_ntu_": 9.1,
    "hydrocarbons_µg_l_": 0.019,
    "water_type": "Saline Lakes",
    "nitrate_µm_": "15 – 40",
    "phosphate_µm_": "1 – 3",
    "ocean_currents_m_s_": "0.05 – 0.2",
    "wave_height_m_": "0.1 – 0.5",
    "status": "Green",
    "latitude": null,
    "longitude": null
  },
  {
    "location": "Bhimtal Lake",
    "date_time": "2025-09-16T06:00:00",
    "temperature_c_": 19.5,
    "ph": 7.62,
    "dissolved_oxygen_mg_l_": 7.8,
    "salinity_ppt_": 0.3,
    "chlorophyll_a_mg_m³_": 2.1,
    "turbidity_ntu_": 3.2,
    "hydrocarbons_µg_l_": 0.009,
    "water_type": "Mountain Lakes",
    "nitrate_µm_": "2 – 8",
    "phosphate_µm_": "0.1 – 0.4",
    "ocean_currents_m_s_": "0.05 – 0.2",
    "wave_height_m_": "0.1 – 0.4",
    "status": "Green",
    "latitude": null,
    "longitude": null
  },
  {
    "location": "Bhimtal Lake",
    "date_time": "2025-09-16T09:00:00",
    "temperature_c_": 20.3,
    "ph": 7.58,
    "dissolved_oxygen_mg_l_": 7.2,
    "salinity_ppt_": 0.3,
    "chlorophyll_a_mg_m³_": 2.6,
    "turbidity_ntu_": 3.8,
    "hydrocarbons_µg_l_": 0.011,
    "water_type": "Mountain Lakes",
    "nitrate_µm_": "2 – 8",
    "phosphate_µm_": "0.1 – 0.4",
    "ocean_currents_m_s_": "0.05 – 0.2",
    "wave_height_m_": "0.1 – 0.4",
    "status": "Green",
    "latitude": null,
    "longitude": null
  },
  {
    "location": "Nainital Lake",
    "date_time": "2025-09-16T06:00:00",
    "temperature_c_": 18.0,
    "ph": 7.45,
    "dissolved_oxygen_mg_l_": 6.9,
    "salinity_ppt_": 0.3,
    "chlorophyll_a_mg_m³_": 3.5,
    "turbidity_ntu_": 5.6,
    "hydrocarbons_µg_l_": 0.014,
    "water_type": "Mountain Lakes",
    "nitrate_µm_": "2 – 8",
    "phosphate_µm_": "0.1 – 0.4",
    "ocean_currents_m_s_": "0.05 – 0.2",
    "wave_height_m_": "0.1 – 0.4",
    "status": "Green",
    "latitude": null,
    "longitude": null
  },
  {
    "location": "Nainital Lake",
    "date_time": "2025-09-16T12:00:00",
    "temperature_c_": 21.0,
    "ph": 7.35,
    "dissolved_oxygen_mg_l_": 5.0,
    "salinity_ppt_": 0.4,
    "chlorophyll_a_mg_m³_": 5.8,
    "turbidity_ntu_": 7.8,
    "hydrocarbons_µg_l_": 0.028,
    "water_type": "Mountain Lakes",
    "nitrate_µm_": "2 – 8",
    "phosphate_µm_": "0.1 – 0.4",
    "ocean_currents_m_s_": "0.05 – 0.2",
    "wave_height_m_": "0.1 – 0.4",
    "status": "Red",
    "latitude": null,
    "longitude": null
  },
  {
    "location": "Sat Tal",
    "date_time": "2025-09-16T06:00:00",
    "temperature_c_": 18.2,
    "ph": 7.68,
    "dissolved_oxygen_mg_l_": 8.2,
    "salinity_ppt_": 0.2,
    "chlorophyll_a_mg_m³_": 1.9,
    "turbidity_ntu_": 2.8,
    "hydrocarbons_µg_l_": 0.006,
    "water_type": "Mountain Lakes",
    "nitrate_µm_": "2 – 8",
    "phosphate_µm_": "0.1 – 0.4",
    "ocean_currents_m_s_": "0.05 – 0.2",
    "wave_height_m_": "0.1 – 0.4",
    "status": "Green",
    "latitude": null,
    "longitude": null
  },
  {
    "location": "Sat Tal",
    "date_time": "2025-09-16T15:00:00",
    "temperature_c_": 21.5,
    "ph": 7.57,
    "dissolved_oxygen_mg_l_": 6.3,
    "salinity_ppt_": 0.3,
    "chlorophyll_a_mg_m³_": 3.6,
    "turbidity_ntu_": 4.8,
    "hydrocarbons_µg_l_": 0.014,
    "water_type": "Mountain Lakes",
    "nitrate_µm_": "2 – 8",
    "phosphate_µm_": "0.1 – 0.4",
    "ocean_currents_m_s_": "0.05 – 0.2",
    "wave_height_m_": "0.1 – 0.4",
    "status": "Yellow",
    "latitude": null,
    "longitude": null
  },
  {
    "location": "Lonar Lake",
    "date_time": "2025-09-16T06:00:00",
    "temperature_c_": 26.5,
    "ph": 9.15,
    "dissolved_oxygen_mg_l_": 6.1,
    "salinity_ppt_": 12.2,
    "chlorophyll_a_mg_m³_": 3.8,
    "turbidity_ntu_": 7.6,
    "hydrocarbons_µg_l_": 0.026,
    "water_type": "Saline Lakes",
    "nitrate_µm_": "15 – 40",
    "phosphate_µm_": "1 – 3",
    "ocean_currents_m_s_": "0.05 – 0.2",
    "wave_height_m_": "0.1 – 0.5",
    "status": "Yellow",
    "latitude": null,
    "longitude": null
  },
  {
    "location": "Lonar Lake",
    "date_time": "2025-09-16T12:00:00",
    "temperature_c_": 29.0,
    "ph": 9.28,
    "dissolved_oxygen_mg_l_": 4.2,
    "salinity_ppt_": 14.6,
    "chlorophyll_a_mg_m³_": 6.0,
    "turbidity_ntu_": 9.7,
    "hydrocarbons_µg_l_": 0.043,
    "water_type": "Saline Lakes",
    "nitrate_µm_": "15 – 40",
    "phosphate_µm_": "1 – 3",
    "ocean_currents_m_s_": "0.05 – 0.2",
    "wave_height_m_": "0.1 – 0.5",
    "status": "Red",
    "latitude": null,
    "longitude": null
  },
  {
    "location": "Lonar Lake",
    "date_time": "2025-09-17T03:00:00",
    "temperature_c_": 25.1,
    "ph": 9.08,
    "dissolved_oxygen_mg_l_": 6.6,
    "salinity_ppt_": 11.8,
    "chlorophyll_a_mg_m³_": 3.6,
    "turbidity_ntu_": 6.9,
    "hydrocarbons_µg_l_": 0.024,
    "water_type": "Saline Lakes",
    "nitrate_µm_": "15 – 40",
    "phosphate_µm_": "1 – 3",
    "ocean_currents_m_s_": "0.05 – 0.2",
    "wave_height_m_": "0.1 – 0.5",
    "status": "Green",
    "latitude": null,
    "longitude": null
  },
  {
    "location": "Tsomoriri Lake",
    "date_time": "2025-09-16T06:00:00",
    "temperature_c_": 7.5,
    "ph": 8.42,
    "dissolved_oxygen_mg_l_": 8.4,
    "salinity_ppt_": 1.1,
    "chlorophyll_a_mg_m³_": 0.6,
    "turbidity_ntu_": 1.9,
    "hydrocarbons_µg_l_": 0.01,
    "water_type": "Mountain Lakes",
    "nitrate_µm_": "2 – 8",
    "phosphate_µm_": "0.1 – 0.4",
    "ocean_currents_m_s_": "0.05 – 0.2",
    "wave_height_m_": "0.1 – 0.4",
    "status": "Green",
    "latitude": null,
    "longitude": null
  },
  {
    "location": "Tsomoriri Lake",
    "date_time": "2025-09-16T12:00:00",
    "temperature_c_": 12.8,
    "ph": 8.5,
    "dissolved_oxygen_mg_l_": 7.6,
    "salinity_ppt_": 1.6,
    "chlorophyll_a_mg_m³_": 1.2,
    "turbidity_ntu_": 2.7,
    "hydrocarbons_µg_l_": 0.016,
    "water_type": "Mountain Lakes",
    "nitrate_µm_": "2 – 8",
    "phosphate_µm_": "0.1 – 0.4",
    "ocean_currents_m_s_": "0.05 – 0.2",
    "wave_height_m_": "0.1 – 0.4",
    "status": "Yellow",
    "latitude": null,
    "longitude": null
  },
  {
    "location": "Pangong Tso",
    "date_time": "2025-09-16T06:00:00",
    "temperature_c_": 6.8,
    "ph": 9.12,
    "dissolved_oxygen_mg_l_": 7.8,
    "salinity_ppt_": 5.4,
    "chlorophyll_a_mg_m³_": 0.7,
    "turbidity_ntu_": 2.4,
    "hydrocarbons_µg_l_": 0.012,
    "water_type": "Mountain Lakes",
    "nitrate_µm_": "2 – 8",
    "phosphate_µm_": "0.1 – 0.4",
    "ocean_currents_m_s_": "0.05 – 0.2",
    "wave_height_m_": "0.1 – 0.4",
    "status": "Green",
    "latitude": null,
    "longitude": null
  },
  {
    "location": "Pangong Tso",
    "date_time": "2025-09-16T12:00:00",
    "temperature_c_": 12.2,
    "ph": 9.18,
    "dissolved_oxygen_mg_l_": 6.6,
    "salinity_ppt_": 6.2,
    "chlorophyll_a_mg_m³_": 1.5,
    "turbidity_ntu_": 3.6,
    "hydrocarbons_µg_l_": 0.021,
    "water_type": "Mountain Lakes",
    "nitrate_µm_": "2 – 8",
    "phosphate_µm_": "0.1 – 0.4",
    "ocean_currents_m_s_": "0.05 – 0.2",
    "wave_height_m_": "0.1 – 0.4",
    "status": "Yellow",
    "latitude": null,
    "longitude": null
  },
  {
    "location": "Hussain Sagar",
    "date_time": "2025-09-16T06:00:00",
    "temperature_c_": 26.8,
    "ph": 7.42,
    "dissolved_oxygen_mg_l_": 4.1,
    "salinity_ppt_": 0.9,
    "chlorophyll_a_mg_m³_": 18.2,
    "turbidity_ntu_": 28.4,
    "hydrocarbons_µg_l_": 0.085,
    "water_type": "Polluted Lakes",
    "nitrate_µm_": "20 – 50",
    "phosphate_µm_": "2 – 4",
    "ocean_currents_m_s_": "0.05 – 0.2",
    "wave_height_m_": "0.1 – 0.4",
    "status": "Yellow",
    "latitude": null,
    "longitude": null
  },
  {
    "location": "Hussain Sagar",
    "date_time": "2025-09-16T09:00:00",
    "temperature_c_": 28.2,
    "ph": 7.38,
    "dissolved_oxygen_mg_l_": 3.7,
    "salinity_ppt_": 1.1,
    "chlorophyll_a_mg_m³_": 22.5,
    "turbidity_ntu_": 32.6,
    "hydrocarbons_µg_l_": 0.093,
    "water_type": "Polluted Lakes",
    "nitrate_µm_": "20 – 50",
    "phosphate_µm_": "2 – 4",
    "ocean_currents_m_s_": "0.05 – 0.2",
    "wave_height_m_": "0.1 – 0.4",
    "status": "Red",
    "latitude": null,
    "longitude": null
  },
  {
    "location": "Hussain Sagar",
    "date_time": "2025-09-17T03:00:00",
    "temperature_c_": 25.2,
    "ph": 7.47,
    "dissolved_oxygen_mg_l_": 5.0,
    "salinity_ppt_": 0.7,
    "chlorophyll_a_mg_m³_": 14.0,
    "turbidity_ntu_": 22.6,
    "hydrocarbons_µg_l_": 0.07,
    "water_type": "Polluted Lakes",
    "nitrate_µm_": "20 – 50",
    "phosphate_µm_": "2 – 4",
    "ocean_currents_m_s_": "0.05 – 0.2",
    "wave_height_m_": "0.1 – 0.4",
    "status": "Green",
    "latitude": null,
    "longitude": null
  },
  {
    "location": "Pong Lake",
    "date_time": "2025-09-16T06:00:00",
    "temperature_c_": 21.4,
    "ph": 7.85,
    "dissolved_oxygen_mg_l_": 7.2,
    "salinity_ppt_": 0.4,
    "chlorophyll_a_mg_m³_": 3.8,
    "turbidity_ntu_": 6.4,
    "hydrocarbons_µg_l_": 0.018,
    "water_type": "Reservoirs",
    "nitrate_µm_": "5 – 15",
    "phosphate_µm_": "0.2 – 1.0",
    "ocean_currents_m_s_": "0.1 – 0.3",
    "wave_height_m_": "0.2 – 0.6",
    "status": "Green",
    "latitude": null,
    "longitude": null
  },
  {
    "location": "Pong Lake",
    "date_time": "2025-09-16T12:00:00",
    "temperature_c_": 26.8,
    "ph": 7.92,
    "dissolved_oxygen_mg_l_": 6.2,
    "salinity_ppt_": 0.7,
    "chlorophyll_a_mg_m³_": 6.2,
    "turbidity_ntu_": 8.9,
    "hydrocarbons_µg_l_": 0.026,
    "water_type": "Reservoirs",
    "nitrate_µm_": "5 – 15",
    "phosphate_µm_": "0.2 – 1.0",
    "ocean_currents_m_s_": "0.1 – 0.3",
    "wave_height_m_": "0.2 – 0.6",
    "status": "Yellow",
    "latitude": null,
    "longitude": null
  },
  {
    "location": "Hirakud Reservoir",
    "date_time": "2025-09-16T06:00:00",
    "temperature_c_": 24.2,
    "ph": 7.72,
    "dissolved_oxygen_mg_l_": 6.8,
    "salinity_ppt_": 0.3,
    "chlorophyll_a_mg_m³_": 4.1,
    "turbidity_ntu_": 7.2,
    "hydrocarbons_µg_l_": 0.022,
    "water_type": "Reservoirs",
    "nitrate_µm_": "5 – 15",
    "phosphate_µm_": "0.2 – 1.0",
    "ocean_currents_m_s_": "0.1 – 0.3",
    "wave_height_m_": "0.2 – 0.6",
    "status": "Green",
    "latitude": null,
    "longitude": null
  },
  {
    "location": "Hirakud Reservoir",
    "date_time": "2025-09-16T09:00:00",
    "temperature_c_": 26.5,
    "ph": 7.75,
    "dissolved_oxygen_mg_l_": 6.2,
    "salinity_ppt_": 0.4,
    "chlorophyll_a_mg_m³_": 5.0,
    "turbidity_ntu_": 8.3,
    "hydrocarbons_µg_l_": 0.027,
    "water_type": "Reservoirs",
    "nitrate_µm_": "5 – 15",
    "phosphate_µm_": "0.2 – 1.0",
    "ocean_currents_m_s_": "0.1 – 0.3",
    "wave_height_m_": "0.2 – 0.6",
    "status": "Yellow",
    "latitude": null,
    "longitude": null
  },
  {
    "location": "Hirakud Reservoir",
    "date_time": "2025-09-16T15:00:00",
    "temperature_c_": 31.1,
    "ph": 7.82,
    "dissolved_oxygen_mg_l_": 5.0,
    "salinity_ppt_": 0.8,
    "chlorophyll_a_mg_m³_": 8.8,
    "turbidity_ntu_": 12.1,
    "hydrocarbons_µg_l_": 0.039,
    "water_type": "Reservoirs",
    "nitrate_µm_": "5 – 15",
    "phosphate_µm_": "0.2 – 1.0",
    "ocean_currents_m_s_": "0.1 – 0.3",
    "wave_height_m_": "0.2 – 0.6",
    "status": "Red",
    "latitude": null,
    "longitude": null
  },
  {
    "location": "Gobind Sagar",
    "date_time": "2025-09-16T06:00:00",
    "temperature_c_": 20.8,
    "ph": 7.65,
    "dissolved_oxygen_mg_l_": 7.1,
    "salinity_ppt_": 0.3,
    "chlorophyll_a_mg_m³_": 3.4,
    "turbidity_ntu_": 6.1,
    "hydrocarbons_µg_l_": 0.018,
    "water_type": "Reservoirs",
    "nitrate_µm_": "5 – 15",
    "phosphate_µm_": "0.2 – 1.0",
    "ocean_currents_m_s_": "0.1 – 0.3",
    "wave_height_m_": "0.2 – 0.6",
    "status": "Green",
    "latitude": null,
    "longitude": null
  },
  {
    "location": "Gobind Sagar",
    "date_time": "2025-09-16T12:00:00",
    "temperature_c_": 25.9,
    "ph": 7.72,
    "dissolved_oxygen_mg_l_": 5.9,
    "salinity_ppt_": 0.6,
    "chlorophyll_a_mg_m³_": 5.7,
    "turbidity_ntu_": 8.5,
    "hydrocarbons_µg_l_": 0.028,
    "water_type": "Reservoirs",
    "nitrate_µm_": "5 – 15",
    "phosphate_µm_": "0.2 – 1.0",
    "ocean_currents_m_s_": "0.1 – 0.3",
    "wave_height_m_": "0.2 – 0.6",
    "status": "Yellow",
    "latitude": null,
    "longitude": null
  },
  {
    "location": "Hussain Sagar",
    "date_time": "2025-09-16T06:00:00",
    "temperature_c_": 27.2,
    "ph": 7.1,
    "dissolved_oxygen_mg_l_": 2.4,
    "salinity_ppt_": 0.9,
    "chlorophyll_a_mg_m³_": 18.5,
    "turbidity_ntu_": 24.0,
    "hydrocarbons_µg_l_": 0.12,
    "water_type": "Polluted Lakes",
    "nitrate_µm_": "20 – 50",
    "phosphate_µm_": "2 – 4",
    "ocean_currents_m_s_": "0.05 – 0.2",
    "wave_height_m_": "0.1 – 0.4",
    "status": "Red",
    "latitude": null,
    "longitude": null
  },
  {
    "location": "Hussain Sagar",
    "date_time": "2025-09-16T09:00:00",
    "temperature_c_": 29.0,
    "ph": 7.15,
    "dissolved_oxygen_mg_l_": 2.0,
    "salinity_ppt_": 1.0,
    "chlorophyll_a_mg_m³_": 22.0,
    "turbidity_ntu_": 28.5,
    "hydrocarbons_µg_l_": 0.145,
    "water_type": "Polluted Lakes",
    "nitrate_µm_": "20 – 50",
    "phosphate_µm_": "2 – 4",
    "ocean_currents_m_s_": "0.05 – 0.2",
    "wave_height_m_": "0.1 – 0.4",
    "status": "Red",
    "latitude": null,
    "longitude": null
  },
  {
    "location": "Rana Pratap Sagar",
    "date_time": "2025-09-16T06:00:00",
    "temperature_c_": 22.4,
    "ph": 7.55,
    "dissolved_oxygen_mg_l_": 7.8,
    "salinity_ppt_": 0.2,
    "chlorophyll_a_mg_m³_": 3.1,
    "turbidity_ntu_": 4.5,
    "hydrocarbons_µg_l_": 0.012,
    "water_type": "Reservoirs",
    "nitrate_µm_": "5 – 15",
    "phosphate_µm_": "0.2 – 1.0",
    "ocean_currents_m_s_": "0.1 – 0.3",
    "wave_height_m_": "0.2 – 0.6",
    "status": "Green",
    "latitude": null,
    "longitude": null
  },
  {
    "location": "Rana Pratap Sagar",
    "date_time": "2025-09-16T15:00:00",
    "temperature_c_": 29.5,
    "ph": 7.72,
    "dissolved_oxygen_mg_l_": 6.0,
    "salinity_ppt_": 0.5,
    "chlorophyll_a_mg_m³_": 6.2,
    "turbidity_ntu_": 7.6,
    "hydrocarbons_µg_l_": 0.021,
    "water_type": "Reservoirs",
    "nitrate_µm_": "5 – 15",
    "phosphate_µm_": "0.2 – 1.0",
    "ocean_currents_m_s_": "0.1 – 0.3",
    "wave_height_m_": "0.2 – 0.6",
    "status": "Yellow",
    "latitude": null,
    "longitude": null
  },
  {
    "location": "Upper Lake (Bhojtal)",
    "date_time": "2025-09-16T06:00:00",
    "temperature_c_": 23.5,
    "ph": 7.5,
    "dissolved_oxygen_mg_l_": 7.6,
    "salinity_ppt_": 0.3,
    "chlorophyll_a_mg_m³_": 3.8,
    "turbidity_ntu_": 5.1,
    "hydrocarbons_µg_l_": 0.016,
    "water_type": "Reservoirs",
    "nitrate_µm_": "5 – 15",
    "phosphate_µm_": "0.2 – 1.0",
    "ocean_currents_m_s_": "0.1 – 0.3",
    "wave_height_m_": "0.2 – 0.6",
    "status": "Green",
    "latitude": null,
    "longitude": null
  },
  {
    "location": "Upper Lake (Bhojtal)",
    "date_time": "2025-09-16T12:00:00",
    "temperature_c_": 28.9,
    "ph": 7.56,
    "dissolved_oxygen_mg_l_": 6.4,
    "salinity_ppt_": 0.4,
    "chlorophyll_a_mg_m³_": 5.5,
    "turbidity_ntu_": 7.2,
    "hydrocarbons_µg_l_": 0.022,
    "water_type": "Reservoirs",
    "nitrate_µm_": "5 – 15",
    "phosphate_µm_": "0.2 – 1.0",
    "ocean_currents_m_s_": "0.1 – 0.3",
    "wave_height_m_": "0.2 – 0.6",
    "status": "Yellow",
    "latitude": null,
    "longitude": null
  },
  {
    "location": "Lower Lake (Chhota Talab)",
    "date_time": "2025-09-16T06:00:00",
    "temperature_c_": 25.4,
    "ph": 7.3,
    "dissolved_oxygen_mg_l_": 4.2,
    "salinity_ppt_": 0.6,
    "chlorophyll_a_mg_m³_": 10.5,
    "turbidity_ntu_": 15.2,
    "hydrocarbons_µg_l_": 0.065,
    "water_type": "Polluted Lakes",
    "nitrate_µm_": "20 – 50",
    "phosphate_µm_": "2 – 4",
    "ocean_currents_m_s_": "0.05 – 0.2",
    "wave_height_m_": "0.1 – 0.4",
    "status": "Yellow",
    "latitude": null,
    "longitude": null
  },
  {
    "location": "Lower Lake (Chhota Talab)",
    "date_time": "2025-09-16T12:00:00",
    "temperature_c_": 31.0,
    "ph": 7.42,
    "dissolved_oxygen_mg_l_": 3.2,
    "salinity_ppt_": 0.9,
    "chlorophyll_a_mg_m³_": 15.6,
    "turbidity_ntu_": 21.0,
    "hydrocarbons_µg_l_": 0.095,
    "water_type": "Polluted Lakes",
    "nitrate_µm_": "20 – 50",
    "phosphate_µm_": "2 – 4",
    "ocean_currents_m_s_": "0.05 – 0.2",
    "wave_height_m_": "0.1 – 0.4",
    "status": "Red",
    "latitude": null,
    "longitude": null
  },
  {
    "location": "Ashtamudi Lake",
    "date_time": "2025-09-16T06:00:00",
    "temperature_c_": 26.8,
    "ph": 7.35,
    "dissolved_oxygen_mg_l_": 5.8,
    "salinity_ppt_": 4.5,
    "chlorophyll_a_mg_m³_": 6.5,
    "turbidity_ntu_": 9.2,
    "hydrocarbons_µg_l_": 0.032,
    "water_type": "Large Lagoon/Estuary Lakes",
    "nitrate_µm_": "10 – 30",
    "phosphate_µm_": "1 – 2",
    "ocean_currents_m_s_": "0.1 – 0.3",
    "wave_height_m_": "0.2 – 0.8",
    "status": "Green",
    "latitude": null,
    "longitude": null
  },
  {
    "location": "Ashtamudi Lake",
    "date_time": "2025-09-16T09:00:00",
    "temperature_c_": 28.4,
    "ph": 7.42,
    "dissolved_oxygen_mg_l_": 5.2,
    "salinity_ppt_": 5.0,
    "chlorophyll_a_mg_m³_": 7.8,
    "turbidity_ntu_": 10.5,
    "hydrocarbons_µg_l_": 0.041,
    "water_type": "Large Lagoon/Estuary Lakes",
    "nitrate_µm_": "10 – 30",
    "phosphate_µm_": "1 – 2",
    "ocean_currents_m_s_": "0.1 – 0.3",
    "wave_height_m_": "0.2 – 0.8",
    "status": "Yellow",
    "latitude": null,
    "longitude": null
  }
]